mcp_dblp/__init__.py
mcp_dblp/dblp_client.py
mcp_dblp/instructions_prompt.md
mcp_dblp/server.py
mcp_dblp/tools.py
mcp_dblp-1.2.1.dist-info/METADATA
mcp_dblp-1.2.1.dist-info/WHEEL
mcp_dblp-1.2.1.dist-info/entry_points.txt
mcp_dblp-1.2.1.dist-info/licenses/LICENSE
mcp_dblp-1.2.1.dist-info/RECORD
