Metadata-Version: 2.4
Name: mcp-dblp
Version: 1.2.1
Summary: An MCP server that provides access to the DBLP computer science bibliography for LLMs.
Project-URL: Homepage, https://github.com/szeider/mcp-dblp
Project-URL: Repository, https://github.com/szeider/mcp-dblp
Project-URL: Issues, https://github.com/szeider/mcp-dblp/issues
Author-email: Stefan Szeider <stefan@szeider.net>
License-Expression: MIT
License-File: LICENSE
Keywords: ai,bibliography,bibtex,citations,dblp,llm,mcp
Classifier: Development Status :: 4 - Beta
Classifier: Intended Audience :: Science/Research
Classifier: License :: OSI Approved :: MIT License
Classifier: Programming Language :: Python :: 3
Classifier: Programming Language :: Python :: 3.11
Classifier: Programming Language :: Python :: 3.12
Classifier: Programming Language :: Python :: 3.13
Classifier: Topic :: Scientific/Engineering
Requires-Python: >=3.11
Requires-Dist: mcp>=1.20.0
Requires-Dist: requests>=2.32.5
